hievpy/__init__.py
hievpy/utils.py
hievpy-1.2.0.dist-info/LICENSE
hievpy-1.2.0.dist-info/METADATA
hievpy-1.2.0.dist-info/WHEEL
hievpy-1.2.0.dist-info/top_level.txt
hievpy-1.2.0.dist-info/RECORD
