Metadata-Version: 2.1
Name: hievpy
Version: 1.2.0
Summary: Python 3 wrapper for the HIEv Data Capture Application API
Home-page: https://github.com/gdevine/hievpy
Author: Gerard Devine, Dan Metzen
Author-email: gerarddevine@gmail.com
License: UNKNOWN
Platform: UNKNOWN
Classifier: Programming Language :: Python :: 3
Classifier: License :: OSI Approved :: MIT License
Classifier: Operating System :: OS Independent
Requires-Dist: pandas
Requires-Dist: tqdm
Requires-Dist: requests
Requires-Dist: certifi
